sim/TestProg_top.v
`timescale 1ns / 1ps
module testProg_top(
stdOutAckInput,
stdOutReadyOutput,
stdOutDataOutput,
clockInput,
resetInput);

   input clockInput;
   input resetInput;

input stdOutAckInput;
output stdOutReadyOutput;
output [31:0] stdOutDataOutput;
//Doable ModuletestProg_top_ParallelDoer0 top code vv 
reg [31:0] dReg;
reg [31:0] eReg;
reg [31:0] aReg;
//Doable ModuletestProg_top_ParallelDoer0_while0 top code vv 
//Doable ModuletestProg_top_ParallelDoer0_while0_SequentualDoerwhileDo top code vv 
//Doable ModuletestProg_top_ParallelDoer0_while0_SequentualDoerwhileDo_while2 top code vv 
reg ModuletestProg_top_ParallelDoer0_while0_SequentualDoerwhileDo_while2_DidTestReg;
reg ModuletestProg_top_ParallelDoer0_while0_SequentualDoerwhileDo_while2_TestPassedReg;
//End of ModuletestProg_top_ParallelDoer0_while0_SequentualDoerwhileDo_while2 top code ^^ 
reg [31:0] ModuletestProg_top_ParallelDoer0_while0_SequentualDoerwhileDo_Reg;

parameter ModuletestProg_top_ParallelDoer0_while0_SequentualDoerwhileDo_ResetStateParam = 0;
parameter ModuletestProg_top_ParallelDoer0_while0_SequentualDoerwhileDo_DoAssign0_StateParam = 1;
parameter ModuletestProg_top_ParallelDoer0_while0_SequentualDoerwhileDo_DoAssign1_StateParam = 2;
parameter ModuletestProg_top_ParallelDoer0_while0_SequentualDoerwhileDo_while2_StateParam = 3;
parameter ModuletestProg_top_ParallelDoer0_while0_SequentualDoerwhileDo_DoAssign3_StateParam = 4;

wire ModuletestProg_top_ParallelDoer0_while0_SequentualDoerwhileDo_DoAssign0_IsActiveWire;
wire ModuletestProg_top_ParallelDoer0_while0_SequentualDoerwhileDo_DoAssign1_IsActiveWire;
wire ModuletestProg_top_ParallelDoer0_while0_SequentualDoerwhileDo_while2_IsActiveWire;
wire ModuletestProg_top_ParallelDoer0_while0_SequentualDoerwhileDo_DoAssign3_IsActiveWire;
//End of ModuletestProg_top_ParallelDoer0_while0_SequentualDoerwhileDo top code ^^ 
reg ModuletestProg_top_ParallelDoer0_while0_DidTestReg;
reg ModuletestProg_top_ParallelDoer0_while0_TestPassedReg;
//End of ModuletestProg_top_ParallelDoer0_while0 top code ^^ 
//Doable ModuletestProg_top_ParallelDoer0_while1 top code vv 
//Doable ModuletestProg_top_ParallelDoer0_while1_SequentualDoerwhileDo top code vv 
reg [31:0] ModuletestProg_top_ParallelDoer0_while1_SequentualDoerwhileDo_Reg;

parameter ModuletestProg_top_ParallelDoer0_while1_SequentualDoerwhileDo_ResetStateParam = 0;
parameter ModuletestProg_top_ParallelDoer0_while1_SequentualDoerwhileDo_DoAssign0_StateParam = 1;

wire ModuletestProg_top_ParallelDoer0_while1_SequentualDoerwhileDo_DoAssign0_IsActiveWire;
//End of ModuletestProg_top_ParallelDoer0_while1_SequentualDoerwhileDo top code ^^ 
reg ModuletestProg_top_ParallelDoer0_while1_DidTestReg;
reg ModuletestProg_top_ParallelDoer0_while1_TestPassedReg;
//End of ModuletestProg_top_ParallelDoer0_while1 top code ^^ 
reg ModuletestProg_top_ParallelDoer0_while0_DoneReg;
reg ModuletestProg_top_ParallelDoer0_while1_DoneReg;
reg ModuletestProg_top_ParallelDoer0_DoAssign2_DoneReg;
//End of ModuletestProg_top_ParallelDoer0 top code ^^ 
//Doable ModuletestProg_top_ParallelDoer0 middle code vv 
always @( posedge clockInput )
if( resetInput ) begin
   dReg <= 0;
end else begin
   if( (ModuletestProg_top_ParallelDoer0_while1_SequentualDoerwhileDo_DoAssign0_IsActiveWire && (((ModuletestProg_top_ParallelDoer0_while0_SequentualDoerwhileDo_DoAssign3_IsActiveWire && (1'b1))))) )begin
      dReg <= (((eReg)));
   end
end
always @( posedge clockInput )
if( resetInput ) begin
   eReg <= 0;
end else begin
   if( (ModuletestProg_top_ParallelDoer0_while0_SequentualDoerwhileDo_DoAssign1_IsActiveWire && (1'b1)) )begin
      eReg <= (0);
   end else if( ((ModuletestProg_top_ParallelDoer0_while0_SequentualDoerwhileDo_while2_DidTestReg && ModuletestProg_top_ParallelDoer0_while0_SequentualDoerwhileDo_while2_TestPassedReg) && ((1'b1) && (1'b1))) )begin
      eReg <= ((eReg) + (1));
   end
end
always @( posedge clockInput )
if( resetInput ) begin
   aReg <= 0;
end else begin
   if( (ModuletestProg_top_ParallelDoer0_while0_SequentualDoerwhileDo_DoAssign0_IsActiveWire && ((1'b1) && (1'b1))) )begin
      aReg <= ((aReg) + (1));
   end
end
//Doable ModuletestProg_top_ParallelDoer0_while0 middle code vv 
//Doable ModuletestProg_top_ParallelDoer0_while0_SequentualDoerwhileDo middle code vv 
//Doable ModuletestProg_top_ParallelDoer0_while0_SequentualDoerwhileDo_while2 middle code vv 
always @( posedge clockInput )
if( resetInput )begin
   ModuletestProg_top_ParallelDoer0_while0_SequentualDoerwhileDo_while2_DidTestReg <= #1 0;
end else begin
   if( !ModuletestProg_top_ParallelDoer0_while0_SequentualDoerwhileDo_while2_IsActiveWire ) begin
       ModuletestProg_top_ParallelDoer0_while0_SequentualDoerwhileDo_while2_DidTestReg <= #1 0;
   end else if( !ModuletestProg_top_ParallelDoer0_while0_SequentualDoerwhileDo_while2_DidTestReg ) begin
       ModuletestProg_top_ParallelDoer0_while0_SequentualDoerwhileDo_while2_DidTestReg <= #1 ((1'b1) && (1'b1));
   end else begin
       ModuletestProg_top_ParallelDoer0_while0_SequentualDoerwhileDo_while2_DidTestReg <= #1 ModuletestProg_top_ParallelDoer0_while0_SequentualDoerwhileDo_while2_TestPassedReg && ModuletestProg_top_ParallelDoer0_while0_SequentualDoerwhileDo_while2_DidTestReg && !((ModuletestProg_top_ParallelDoer0_while0_SequentualDoerwhileDo_while2_DidTestReg && ModuletestProg_top_ParallelDoer0_while0_SequentualDoerwhileDo_while2_TestPassedReg) && ((1'b1) && (1'b1)));
   end
end
always @( posedge clockInput )
if( resetInput )begin
   ModuletestProg_top_ParallelDoer0_while0_SequentualDoerwhileDo_while2_TestPassedReg <= #1 0;
end else begin
   if( !ModuletestProg_top_ParallelDoer0_while0_SequentualDoerwhileDo_while2_IsActiveWire ) begin
       ModuletestProg_top_ParallelDoer0_while0_SequentualDoerwhileDo_while2_TestPassedReg <= #1 0;
   end else if( !ModuletestProg_top_ParallelDoer0_while0_SequentualDoerwhileDo_while2_DidTestReg ) begin
       ModuletestProg_top_ParallelDoer0_while0_SequentualDoerwhileDo_while2_TestPassedReg <= #1 ((1'b1) && (1'b1)) && ((eReg) < (aReg));
   end else if( ((ModuletestProg_top_ParallelDoer0_while0_SequentualDoerwhileDo_while2_DidTestReg && ModuletestProg_top_ParallelDoer0_while0_SequentualDoerwhileDo_while2_TestPassedReg) && ((1'b1) && (1'b1))) ) begin
       ModuletestProg_top_ParallelDoer0_while0_SequentualDoerwhileDo_while2_TestPassedReg <= #1 0;
   end
end
//End of ModuletestProg_top_ParallelDoer0_while0_SequentualDoerwhileDo_while2 middle code ^^ 
always @( posedge clockInput )
if( resetInput || !( (ModuletestProg_top_ParallelDoer0_while0_DidTestReg && ModuletestProg_top_ParallelDoer0_while0_TestPassedReg)) )begin
   ModuletestProg_top_ParallelDoer0_while0_SequentualDoerwhileDo_Reg <= ModuletestProg_top_ParallelDoer0_while0_SequentualDoerwhileDo_ResetStateParam;
end else case( ModuletestProg_top_ParallelDoer0_while0_SequentualDoerwhileDo_Reg)
   ModuletestProg_top_ParallelDoer0_while0_SequentualDoerwhileDo_ResetStateParam: begin
       if( (ModuletestProg_top_ParallelDoer0_while0_DidTestReg && ModuletestProg_top_ParallelDoer0_while0_TestPassedReg) )begin
          ModuletestProg_top_ParallelDoer0_while0_SequentualDoerwhileDo_Reg <= ModuletestProg_top_ParallelDoer0_while0_SequentualDoerwhileDo_DoAssign0_StateParam;
       end
   end
   ModuletestProg_top_ParallelDoer0_while0_SequentualDoerwhileDo_DoAssign0_StateParam: begin
      if( (ModuletestProg_top_ParallelDoer0_while0_SequentualDoerwhileDo_DoAssign0_IsActiveWire && ((1'b1) && (1'b1))) ) begin
         ModuletestProg_top_ParallelDoer0_while0_SequentualDoerwhileDo_Reg <= ModuletestProg_top_ParallelDoer0_while0_SequentualDoerwhileDo_DoAssign1_StateParam;
      end
   end
   ModuletestProg_top_ParallelDoer0_while0_SequentualDoerwhileDo_DoAssign1_StateParam: begin
      if( (ModuletestProg_top_ParallelDoer0_while0_SequentualDoerwhileDo_DoAssign1_IsActiveWire && (1'b1)) ) begin
         ModuletestProg_top_ParallelDoer0_while0_SequentualDoerwhileDo_Reg <= ModuletestProg_top_ParallelDoer0_while0_SequentualDoerwhileDo_while2_StateParam;
      end
   end
   ModuletestProg_top_ParallelDoer0_while0_SequentualDoerwhileDo_while2_StateParam: begin
      if( (ModuletestProg_top_ParallelDoer0_while0_SequentualDoerwhileDo_while2_DidTestReg && !ModuletestProg_top_ParallelDoer0_while0_SequentualDoerwhileDo_while2_TestPassedReg) ) begin
         ModuletestProg_top_ParallelDoer0_while0_SequentualDoerwhileDo_Reg <= ModuletestProg_top_ParallelDoer0_while0_SequentualDoerwhileDo_DoAssign3_StateParam;
      end
   end
   ModuletestProg_top_ParallelDoer0_while0_SequentualDoerwhileDo_DoAssign3_StateParam: begin
      if( (((ModuletestProg_top_ParallelDoer0_while1_SequentualDoerwhileDo_DoAssign0_IsActiveWire && (ModuletestProg_top_ParallelDoer0_while1_SequentualDoerwhileDo_DoAssign0_IsActiveWire && (((ModuletestProg_top_ParallelDoer0_while0_SequentualDoerwhileDo_DoAssign3_IsActiveWire && (1'b1)))))))) ) begin
         ModuletestProg_top_ParallelDoer0_while0_SequentualDoerwhileDo_Reg <= ModuletestProg_top_ParallelDoer0_while0_SequentualDoerwhileDo_ResetStateParam;
      end
   end
   default: begin
             ModuletestProg_top_ParallelDoer0_while0_SequentualDoerwhileDo_Reg <= ModuletestProg_top_ParallelDoer0_while0_SequentualDoerwhileDo_ResetStateParam;
   end
endcase
//End of ModuletestProg_top_ParallelDoer0_while0_SequentualDoerwhileDo middle code ^^ 
always @( posedge clockInput )
if( resetInput )begin
   ModuletestProg_top_ParallelDoer0_while0_DidTestReg <= #1 0;
end else begin
   if( !( 1'b1 && !ModuletestProg_top_ParallelDoer0_while0_DoneReg ) ) begin
       ModuletestProg_top_ParallelDoer0_while0_DidTestReg <= #1 0;
   end else if( !ModuletestProg_top_ParallelDoer0_while0_DidTestReg ) begin
       ModuletestProg_top_ParallelDoer0_while0_DidTestReg <= #1 (1'b1);
   end else begin
       ModuletestProg_top_ParallelDoer0_while0_DidTestReg <= #1 ModuletestProg_top_ParallelDoer0_while0_TestPassedReg && ModuletestProg_top_ParallelDoer0_while0_DidTestReg && !(((ModuletestProg_top_ParallelDoer0_while1_SequentualDoerwhileDo_DoAssign0_IsActiveWire && (ModuletestProg_top_ParallelDoer0_while1_SequentualDoerwhileDo_DoAssign0_IsActiveWire && (((ModuletestProg_top_ParallelDoer0_while0_SequentualDoerwhileDo_DoAssign3_IsActiveWire && (1'b1))))))));
   end
end
always @( posedge clockInput )
if( resetInput )begin
   ModuletestProg_top_ParallelDoer0_while0_TestPassedReg <= #1 0;
end else begin
   if( !( 1'b1 && !ModuletestProg_top_ParallelDoer0_while0_DoneReg ) ) begin
       ModuletestProg_top_ParallelDoer0_while0_TestPassedReg <= #1 0;
   end else if( !ModuletestProg_top_ParallelDoer0_while0_DidTestReg ) begin
       ModuletestProg_top_ParallelDoer0_while0_TestPassedReg <= #1 (1'b1) && (1);
   end else if( (((ModuletestProg_top_ParallelDoer0_while1_SequentualDoerwhileDo_DoAssign0_IsActiveWire && (ModuletestProg_top_ParallelDoer0_while1_SequentualDoerwhileDo_DoAssign0_IsActiveWire && (((ModuletestProg_top_ParallelDoer0_while0_SequentualDoerwhileDo_DoAssign3_IsActiveWire && (1'b1)))))))) ) begin
       ModuletestProg_top_ParallelDoer0_while0_TestPassedReg <= #1 0;
   end
end
//End of ModuletestProg_top_ParallelDoer0_while0 middle code ^^ 
//Doable ModuletestProg_top_ParallelDoer0_while1 middle code vv 
//Doable ModuletestProg_top_ParallelDoer0_while1_SequentualDoerwhileDo middle code vv 
always @( posedge clockInput )
if( resetInput || !( (ModuletestProg_top_ParallelDoer0_while1_DidTestReg && ModuletestProg_top_ParallelDoer0_while1_TestPassedReg)) )begin
   ModuletestProg_top_ParallelDoer0_while1_SequentualDoerwhileDo_Reg <= ModuletestProg_top_ParallelDoer0_while1_SequentualDoerwhileDo_ResetStateParam;
end else case( ModuletestProg_top_ParallelDoer0_while1_SequentualDoerwhileDo_Reg)
   ModuletestProg_top_ParallelDoer0_while1_SequentualDoerwhileDo_ResetStateParam: begin
       if( (ModuletestProg_top_ParallelDoer0_while1_DidTestReg && ModuletestProg_top_ParallelDoer0_while1_TestPassedReg) )begin
          ModuletestProg_top_ParallelDoer0_while1_SequentualDoerwhileDo_Reg <= ModuletestProg_top_ParallelDoer0_while1_SequentualDoerwhileDo_DoAssign0_StateParam;
       end
   end
   ModuletestProg_top_ParallelDoer0_while1_SequentualDoerwhileDo_DoAssign0_StateParam: begin
      if( (ModuletestProg_top_ParallelDoer0_while1_SequentualDoerwhileDo_DoAssign0_IsActiveWire && (((ModuletestProg_top_ParallelDoer0_while0_SequentualDoerwhileDo_DoAssign3_IsActiveWire && (1'b1))))) ) begin
         ModuletestProg_top_ParallelDoer0_while1_SequentualDoerwhileDo_Reg <= ModuletestProg_top_ParallelDoer0_while1_SequentualDoerwhileDo_ResetStateParam;
      end
   end
   default: begin
             ModuletestProg_top_ParallelDoer0_while1_SequentualDoerwhileDo_Reg <= ModuletestProg_top_ParallelDoer0_while1_SequentualDoerwhileDo_ResetStateParam;
   end
endcase
//End of ModuletestProg_top_ParallelDoer0_while1_SequentualDoerwhileDo middle code ^^ 
always @( posedge clockInput )
if( resetInput )begin
   ModuletestProg_top_ParallelDoer0_while1_DidTestReg <= #1 0;
end else begin
   if( !( 1'b1 && !ModuletestProg_top_ParallelDoer0_while1_DoneReg ) ) begin
       ModuletestProg_top_ParallelDoer0_while1_DidTestReg <= #1 0;
   end else if( !ModuletestProg_top_ParallelDoer0_while1_DidTestReg ) begin
       ModuletestProg_top_ParallelDoer0_while1_DidTestReg <= #1 (1'b1);
   end else begin
       ModuletestProg_top_ParallelDoer0_while1_DidTestReg <= #1 ModuletestProg_top_ParallelDoer0_while1_TestPassedReg && ModuletestProg_top_ParallelDoer0_while1_DidTestReg && !(ModuletestProg_top_ParallelDoer0_while1_SequentualDoerwhileDo_DoAssign0_IsActiveWire && (((ModuletestProg_top_ParallelDoer0_while0_SequentualDoerwhileDo_DoAssign3_IsActiveWire && (1'b1)))));
   end
end
always @( posedge clockInput )
if( resetInput )begin
   ModuletestProg_top_ParallelDoer0_while1_TestPassedReg <= #1 0;
end else begin
   if( !( 1'b1 && !ModuletestProg_top_ParallelDoer0_while1_DoneReg ) ) begin
       ModuletestProg_top_ParallelDoer0_while1_TestPassedReg <= #1 0;
   end else if( !ModuletestProg_top_ParallelDoer0_while1_DidTestReg ) begin
       ModuletestProg_top_ParallelDoer0_while1_TestPassedReg <= #1 (1'b1) && (1);
   end else if( (ModuletestProg_top_ParallelDoer0_while1_SequentualDoerwhileDo_DoAssign0_IsActiveWire && (((ModuletestProg_top_ParallelDoer0_while0_SequentualDoerwhileDo_DoAssign3_IsActiveWire && (1'b1))))) ) begin
       ModuletestProg_top_ParallelDoer0_while1_TestPassedReg <= #1 0;
   end
end
//End of ModuletestProg_top_ParallelDoer0_while1 middle code ^^ 
always @( posedge clockInput )
if( resetInput ) begin
   ModuletestProg_top_ParallelDoer0_while0_DoneReg <= #1 0;
   ModuletestProg_top_ParallelDoer0_while1_DoneReg <= #1 0;
   ModuletestProg_top_ParallelDoer0_DoAssign2_DoneReg <= #1 0;
end else begin
   if( !1'b1 || (( ModuletestProg_top_ParallelDoer0_while0_DoneReg || (ModuletestProg_top_ParallelDoer0_while0_DidTestReg && !ModuletestProg_top_ParallelDoer0_while0_TestPassedReg)) && ( ModuletestProg_top_ParallelDoer0_while1_DoneReg || (ModuletestProg_top_ParallelDoer0_while1_DidTestReg && !ModuletestProg_top_ParallelDoer0_while1_TestPassedReg)) && ( ModuletestProg_top_ParallelDoer0_DoAssign2_DoneReg || stdOutAckInput)) ) begin
       ModuletestProg_top_ParallelDoer0_while0_DoneReg <= #1 0;
       ModuletestProg_top_ParallelDoer0_while1_DoneReg <= #1 0;
       ModuletestProg_top_ParallelDoer0_DoAssign2_DoneReg <= #1 0;
    end else begin
       ModuletestProg_top_ParallelDoer0_while0_DoneReg <= #1 ModuletestProg_top_ParallelDoer0_while0_DoneReg || (ModuletestProg_top_ParallelDoer0_while0_DidTestReg && !ModuletestProg_top_ParallelDoer0_while0_TestPassedReg);
       ModuletestProg_top_ParallelDoer0_while1_DoneReg <= #1 ModuletestProg_top_ParallelDoer0_while1_DoneReg || (ModuletestProg_top_ParallelDoer0_while1_DidTestReg && !ModuletestProg_top_ParallelDoer0_while1_TestPassedReg);
       ModuletestProg_top_ParallelDoer0_DoAssign2_DoneReg <= #1 ModuletestProg_top_ParallelDoer0_DoAssign2_DoneReg || stdOutAckInput;
    end
end
//End of ModuletestProg_top_ParallelDoer0 middle code ^^ 
assign stdOutReadyOutput = ( (( 1'b1 && !ModuletestProg_top_ParallelDoer0_DoAssign2_DoneReg ) && (1'b1)) );
assign stdOutDataOutput = ((1));
//Doable ModuletestProg_top_ParallelDoer0 bottom code vv 
//Doable ModuletestProg_top_ParallelDoer0_while0 bottom code vv 
//Doable ModuletestProg_top_ParallelDoer0_while0_SequentualDoerwhileDo bottom code vv 
assign ModuletestProg_top_ParallelDoer0_while0_SequentualDoerwhileDo_DoAssign0_IsActiveWire = (ModuletestProg_top_ParallelDoer0_while0_SequentualDoerwhileDo_Reg == ModuletestProg_top_ParallelDoer0_while0_SequentualDoerwhileDo_DoAssign0_StateParam );
assign ModuletestProg_top_ParallelDoer0_while0_SequentualDoerwhileDo_DoAssign1_IsActiveWire = (ModuletestProg_top_ParallelDoer0_while0_SequentualDoerwhileDo_Reg == ModuletestProg_top_ParallelDoer0_while0_SequentualDoerwhileDo_DoAssign1_StateParam );
assign ModuletestProg_top_ParallelDoer0_while0_SequentualDoerwhileDo_while2_IsActiveWire = (ModuletestProg_top_ParallelDoer0_while0_SequentualDoerwhileDo_Reg == ModuletestProg_top_ParallelDoer0_while0_SequentualDoerwhileDo_while2_StateParam );
assign ModuletestProg_top_ParallelDoer0_while0_SequentualDoerwhileDo_DoAssign3_IsActiveWire = (ModuletestProg_top_ParallelDoer0_while0_SequentualDoerwhileDo_Reg == ModuletestProg_top_ParallelDoer0_while0_SequentualDoerwhileDo_DoAssign3_StateParam );
//End of ModuletestProg_top_ParallelDoer0_while0_SequentualDoerwhileDo bottom code ^^ 
//End of ModuletestProg_top_ParallelDoer0_while0 bottom code ^^ 
//Doable ModuletestProg_top_ParallelDoer0_while1 bottom code vv 
//Doable ModuletestProg_top_ParallelDoer0_while1_SequentualDoerwhileDo bottom code vv 
assign ModuletestProg_top_ParallelDoer0_while1_SequentualDoerwhileDo_DoAssign0_IsActiveWire = (ModuletestProg_top_ParallelDoer0_while1_SequentualDoerwhileDo_Reg == ModuletestProg_top_ParallelDoer0_while1_SequentualDoerwhileDo_DoAssign0_StateParam );
//End of ModuletestProg_top_ParallelDoer0_while1_SequentualDoerwhileDo bottom code ^^ 
//End of ModuletestProg_top_ParallelDoer0_while1 bottom code ^^ 
//End of ModuletestProg_top_ParallelDoer0 bottom code ^^ 
endmodule

sim/testProg_top_tb.v
`timescale 1ns / 1ps

////////////////////////////////////////////////////////////////////////////////
// Company: 
// Engineer:
//
// Create Date:   14:40:01 10/20/2012
// Design Name:   testProg_top
// Module Name:   C:/Shared_Docs/lunch/ve/ise/veTestProj/testProg_topVTF.v
// Project Name:  veTestProj
// Target Device:  
// Tool versions:  
// Description: 
//
// Verilog Test Fixture created by ISE for module: testProg_top
//
// Dependencies:
// 
// Revision:
// Revision 0.01 - File Created
// Additional Comments:
// 
////////////////////////////////////////////////////////////////////////////////

module testProg_top_tb;

	// Inputs
	reg stdOutAckInput;
	reg clockInput;
	reg resetInput;

	// Outputs
	wire stdOutReadyOutput;
	wire [31:0] stdOutDataOutput;
	
	// Clock generator
	always begin
		#5  clockInput = ~clockInput; // Toggle clock every 5 ticks
	end

	// Instantiate the Unit Under Test (UUT)
	testProg_top uut (
		.stdOutAckInput(stdOutAckInput), 
		.stdOutReadyOutput(stdOutReadyOutput), 
		.stdOutDataOutput(stdOutDataOutput), 
		.clockInput(clockInput), 
		.resetInput(resetInput)
	);

	initial begin
		$dumpfile("testProg_top.vcd");
		$dumpvars(0,uut);
	
		// Initialize Inputs
		stdOutAckInput = 0;
		clockInput = 0;
		resetInput = 0;

		// Wait 100 ns for global reset to finish
		#100;
        
		// Add stimulus here
		@(posedge clockInput);
		resetInput = 1;
		@(posedge clockInput);
		resetInput = 0;

		#1000;
		$finish();

	end
      
endmodule

sim/testProg_top.vcd
$date
	Wed Nov 21 17:09:08 2012
$end
$version
	Icarus Verilog
$end
$timescale
	1ps
$end
$scope module testProg_top_tb $end
$scope module uut $end
$var wire 1 ! ModuletestProg_top_ParallelDoer0_while0_SequentualDoerwhileDo_DoAssign0_IsActiveWire $end
$var wire 1 " ModuletestProg_top_ParallelDoer0_while0_SequentualDoerwhileDo_DoAssign1_IsActiveWire $end
$var wire 1 # ModuletestProg_top_ParallelDoer0_while0_SequentualDoerwhileDo_DoAssign3_IsActiveWire $end
$var wire 1 $ ModuletestProg_top_ParallelDoer0_while0_SequentualDoerwhileDo_while2_IsActiveWire $end
$var wire 1 % ModuletestProg_top_ParallelDoer0_while1_SequentualDoerwhileDo_DoAssign0_IsActiveWire $end
$var wire 1 & clockInput $end
$var wire 1 ' resetInput $end
$var wire 1 ( stdOutAckInput $end
$var wire 32 ) stdOutDataOutput [31:0] $end
$var wire 1 * stdOutReadyOutput $end
$var reg 1 + ModuletestProg_top_ParallelDoer0_DoAssign2_DoneReg $end
$var reg 1 , ModuletestProg_top_ParallelDoer0_while0_DidTestReg $end
$var reg 1 - ModuletestProg_top_ParallelDoer0_while0_DoneReg $end
$var reg 32 . ModuletestProg_top_ParallelDoer0_while0_SequentualDoerwhileDo_Reg [31:0] $end
$var reg 1 / ModuletestProg_top_ParallelDoer0_while0_SequentualDoerwhileDo_while2_DidTestReg $end
$var reg 1 0 ModuletestProg_top_ParallelDoer0_while0_SequentualDoerwhileDo_while2_TestPassedReg $end
$var reg 1 1 ModuletestProg_top_ParallelDoer0_while0_TestPassedReg $end
$var reg 1 2 ModuletestProg_top_ParallelDoer0_while1_DidTestReg $end
$var reg 1 3 ModuletestProg_top_ParallelDoer0_while1_DoneReg $end
$var reg 32 4 ModuletestProg_top_ParallelDoer0_while1_SequentualDoerwhileDo_Reg [31:0] $end
$var reg 1 5 ModuletestProg_top_ParallelDoer0_while1_TestPassedReg $end
$var reg 32 6 aReg [31:0] $end
$var reg 32 7 dReg [31:0] $end
$var reg 32 8 eReg [31:0] $end
$upscope $end
$upscope $end
$enddefinitions $end
#0
$dumpvars
bx 8
bx 7
bx 6
x5
bx 4
x3
x2
x1
x0
x/
bx .
x-
x,
x+
x*
b1 )
0(
0'
0&
x%
x$
x#
x"
x!
$end
#5000
b0 .
0!
0"
0$
0#
b0 4
0%
1&
#10000
0&
#15000
1&
#16000
00
0/
#20000
0&
#25000
1&
#30000
0&
#35000
1&
#40000
0&
#45000
1&
#50000
0&
#55000
1&
#60000
0&
#65000
1&
#70000
0&
#75000
1&
#80000
0&
#85000
1&
#90000
0&
#95000
1&
#100000
0&
#105000
b0 7
b0 8
b0 6
1'
1&
#106000
1*
0,
01
02
05
0+
03
0-
#110000
0&
#115000
0'
1&
#120000
0&
#125000
1&
#126000
1,
11
12
15
#130000
0&
#135000
b1 4
1%
b1 .
1!
1&
#140000
0&
#145000
b1 6
b10 .
0!
1"
1&
#150000
0&
#155000
b11 .
0"
1$
1&
#160000
0&
#165000
1&
#166000
1/
10
#170000
0&
#175000
b1 8
1&
#176000
00
0/
#180000
0&
#185000
1&
#186000
1/
#190000
0&
#195000
b100 .
0$
1#
1&
#196000
0/
#200000
0&
#205000
b1 7
b0 .
0#
b0 4
0%
1&
#206000
0,
01
02
05
#210000
0&
#215000
1&
#216000
15
12
11
1,
#220000
0&
#225000
b1 .
1!
b1 4
1%
1&
#230000
0&
#235000
b10 .
0!
1"
b10 6
1&
#240000
0&
#245000
b0 8
b11 .
0"
1$
1&
#250000
0&
#255000
1&
#256000
10
1/
#260000
0&
#265000
b1 8
1&
#266000
0/
00
#270000
0&
#275000
1&
#276000
10
1/
#280000
0&
#285000
b10 8
1&
#286000
0/
00
#290000
0&
#295000
1&
#296000
1/
#300000
0&
#305000
b100 .
0$
1#
1&
#306000
0/
#310000
0&
#315000
b0 4
0%
b0 .
0#
b10 7
1&
#316000
05
02
01
0,
#320000
0&
#325000
1&
#326000
1,
11
12
15
#330000
0&
#335000
b1 4
1%
b1 .
1!
1&
#340000
0&
#345000
b11 6
b10 .
0!
1"
1&
#350000
0&
#355000
b11 .
0"
1$
b0 8
1&
#360000
0&
#365000
1&
#366000
1/
10
#370000
0&
#375000
b1 8
1&
#376000
00
0/
#380000
0&
#385000
1&
#386000
1/
10
#390000
0&
#395000
b10 8
1&
#396000
00
0/
#400000
0&
#405000
1&
#406000
1/
10
#410000
0&
#415000
b11 8
1&
#416000
00
0/
#420000
0&
#425000
1&
#426000
1/
#430000
0&
#435000
b100 .
0$
1#
1&
#436000
0/
#440000
0&
#445000
b11 7
b0 .
0#
b0 4
0%
1&
#446000
0,
01
02
05
#450000
0&
#455000
1&
#456000
15
12
11
1,
#460000
0&
#465000
b1 .
1!
b1 4
1%
1&
#470000
0&
#475000
b10 .
0!
1"
b100 6
1&
#480000
0&
#485000
b0 8
b11 .
0"
1$
1&
#490000
0&
#495000
1&
#496000
10
1/
#500000
0&
#505000
b1 8
1&
#506000
0/
00
#510000
0&
#515000
1&
#516000
10
1/
#520000
0&
#525000
b10 8
1&
#526000
0/
00
#530000
0&
#535000
1&
#536000
10
1/
#540000
0&
#545000
b11 8
1&
#546000
0/
00
#550000
0&
#555000
1&
#556000
10
1/
#560000
0&
#565000
b100 8
1&
#566000
0/
00
#570000
0&
#575000
1&
#576000
1/
#580000
0&
#585000
b100 .
0$
1#
1&
#586000
0/
#590000
0&
#595000
b0 4
0%
b0 .
0#
b100 7
1&
#596000
05
02
01
0,
#600000
0&
#605000
1&
#606000
1,
11
12
15
#610000
0&
#615000
b1 4
1%
b1 .
1!
1&
#620000
0&
#625000
b101 6
b10 .
0!
1"
1&
#630000
0&
#635000
b11 .
0"
1$
b0 8
1&
#640000
0&
#645000
1&
#646000
1/
10
#650000
0&
#655000
b1 8
1&
#656000
00
0/
#660000
0&
#665000
1&
#666000
1/
10
#670000
0&
#675000
b10 8
1&
#676000
00
0/
#680000
0&
#685000
1&
#686000
1/
10
#690000
0&
#695000
b11 8
1&
#696000
00
0/
#700000
0&
#705000
1&
#706000
1/
10
#710000
0&
#715000
b100 8
1&
#716000
00
0/
#720000
0&
#725000
1&
#726000
1/
10
#730000
0&
#735000
b101 8
1&
#736000
00
0/
#740000
0&
#745000
1&
#746000
1/
#750000
0&
#755000
b100 .
0$
1#
1&
#756000
0/
#760000
0&
#765000
b101 7
b0 .
0#
b0 4
0%
1&
#766000
0,
01
02
05
#770000
0&
#775000
1&
#776000
15
12
11
1,
#780000
0&
#785000
b1 .
1!
b1 4
1%
1&
#790000
0&
#795000
b10 .
0!
1"
b110 6
1&
#800000
0&
#805000
b0 8
b11 .
0"
1$
1&
#810000
0&
#815000
1&
#816000
10
1/
#820000
0&
#825000
b1 8
1&
#826000
0/
00
#830000
0&
#835000
1&
#836000
10
1/
#840000
0&
#845000
b10 8
1&
#846000
0/
00
#850000
0&
#855000
1&
#856000
10
1/
#860000
0&
#865000
b11 8
1&
#866000
0/
00
#870000
0&
#875000
1&
#876000
10
1/
#880000
0&
#885000
b100 8
1&
#886000
0/
00
#890000
0&
#895000
1&
#896000
10
1/
#900000
0&
#905000
b101 8
1&
#906000
0/
00
#910000
0&
#915000
1&
#916000
10
1/
#920000
0&
#925000
b110 8
1&
#926000
0/
00
#930000
0&
#935000
1&
#936000
1/
#940000
0&
#945000
b100 .
0$
1#
1&
#946000
0/
#950000
0&
#955000
b0 4
0%
b0 .
0#
b110 7
1&
#956000
05
02
01
0,
#960000
0&
#965000
1&
#966000
1,
11
12
15
#970000
0&
#975000
b1 4
1%
b1 .
1!
1&
#980000
0&
#985000
b111 6
b10 .
0!
1"
1&
#990000
0&
#995000
b11 .
0"
1$
b0 8
1&
#1000000
0&
#1005000
1&
#1006000
1/
10
#1010000
0&
#1015000
b1 8
1&
#1016000
00
0/
#1020000
0&
#1025000
1&
#1026000
1/
10
#1030000
0&
#1035000
b10 8
1&
#1036000
00
0/
#1040000
0&
#1045000
1&
#1046000
1/
10
#1050000
0&
#1055000
b11 8
1&
#1056000
00
0/
#1060000
0&
#1065000
1&
#1066000
1/
10
#1070000
0&
#1075000
b100 8
1&
#1076000
00
0/
#1080000
0&
#1085000
1&
#1086000
1/
10
#1090000
0&
#1095000
b101 8
1&
#1096000
00
0/
#1100000
0&
#1105000
1&
#1106000
1/
10
#1110000
0&
#1115000
b110 8
1&
